Metadata-Version: 2.4
Name: mypy-raise
Version: 0.2.0
Summary: A mypy plugin to check for raised exceptions
Author-email: "Diego J. Romero Lopez" <diegojromerolopez@example.com>
License: MIT License
Project-URL: Homepage, https://github.com/diegojromerolopez/mypy-raise
Project-URL: Bug Tracker, https://github.com/diegojromerolopez/mypy-raise/issues
Keywords: mypy,plugin,exception,raise
Classifier: Programming Language :: Python :: 3
Classifier: License :: OSI Approved :: MIT License
Classifier: Operating System :: OS Independent
Classifier: Typing :: Typed
Requires-Python: >=3.10
License-File: LICENSE
Requires-Dist: mypy>=1.0.0
Dynamic: license-file
